{
  "initialUrl": "https://amagi.tv/",
  "finalUrl": "chrome-error://chromewebdata/",
  "timeout": false,
  "testStarted": 1774993528800,
  "testFinished": 1774993535871,
  "data": {
    "requests": [
      {
        "url": "https://amagi.tv/",
        "method": "GET",
        "type": "Document",
        "size": 184483,
        "responseBodyHash": "c2d537e5fd19ddb447302f80fe44e42364a5a705b762de88c66a122879c4306d",
        "failureReason": "net::ERR_CONNECTION_RESET",
        "initiators": [],
        "time": 1.5290949999998702
      }
    ],
    "cookies": [],
    "targets": [
      {
        "type": "page",
        "url": "about:blank"
      }
    ],
    "apis": {
      "callStats": {},
      "savedCalls": []
    }
  }
}