{
  "initialUrl": "https://deepl.com/",
  "finalUrl": "chrome-error://chromewebdata/",
  "timeout": false,
  "testStarted": 1774990827362,
  "testFinished": 1774990835191,
  "data": {
    "requests": [
      {
        "url": "https://deepl.com/",
        "method": "GET",
        "type": "Document",
        "size": 184558,
        "responseBodyHash": "089be185cffff2b66e85729cf8bb4b0d8723bb2eb2f396b19e3b9b278048193f",
        "failureReason": "net::ERR_INTERNET_DISCONNECTED",
        "initiators": [],
        "time": 0.03140300000086427
      }
    ],
    "cookies": [],
    "targets": [
      {
        "type": "page",
        "url": "about:blank"
      }
    ],
    "apis": {
      "callStats": {},
      "savedCalls": []
    }
  }
}