{
  "initialUrl": "https://gamepass.com/",
  "finalUrl": "chrome-error://chromewebdata/",
  "timeout": false,
  "testStarted": 1774989306905,
  "testFinished": 1774989311815,
  "data": {
    "requests": [
      {
        "url": "https://gamepass.com/",
        "method": "GET",
        "type": "Document",
        "size": 133311,
        "responseBodyHash": "c95a4bc848d9f305d0b784457d052eea1c43261cfe77e852e62cb59b86357219",
        "failureReason": "net::ERR_CERT_COMMON_NAME_INVALID",
        "initiators": [],
        "time": 0.4174280000006547
      }
    ],
    "cookies": [],
    "targets": [
      {
        "type": "page",
        "url": "about:blank"
      }
    ],
    "apis": {
      "callStats": {},
      "savedCalls": []
    }
  }
}