{
  "initialUrl": "https://herokuapp.com/",
  "finalUrl": "chrome-error://chromewebdata/",
  "timeout": false,
  "testStarted": 1774992715450,
  "testFinished": 1774992721861,
  "data": {
    "requests": [
      {
        "url": "https://herokuapp.com/",
        "method": "GET",
        "type": "Document",
        "size": 183756,
        "responseBodyHash": "0bd0a236edb75d14ec0cde98a9ba9e76dce3d4231249440fd87de8e15b3e2b57",
        "failureReason": "net::ERR_SSL_UNRECOGNIZED_NAME_ALERT",
        "initiators": [],
        "time": 0.1362810000009631
      }
    ],
    "cookies": [],
    "targets": [
      {
        "type": "page",
        "url": "about:blank"
      }
    ],
    "apis": {
      "callStats": {},
      "savedCalls": []
    }
  }
}