{
  "initialUrl": "https://nexthink.cloud/",
  "finalUrl": "chrome-error://chromewebdata/",
  "timeout": false,
  "testStarted": 1774993974257,
  "testFinished": 1774993982855,
  "data": {
    "requests": [
      {
        "url": "https://nexthink.cloud/",
        "method": "GET",
        "type": "Document",
        "size": 183815,
        "responseBodyHash": "4e5ad5316178efbad878287a8fe7a05a1932e2f64ead6c9ae15157d63961eef9",
        "failureReason": "net::ERR_NAME_NOT_RESOLVED",
        "initiators": [],
        "time": 0.08429699999942386
      }
    ],
    "cookies": [],
    "targets": [
      {
        "type": "page",
        "url": "about:blank"
      }
    ],
    "apis": {
      "callStats": {},
      "savedCalls": []
    }
  }
}