{
  "initialUrl": "https://t-msedge.net/",
  "finalUrl": "chrome-error://chromewebdata/",
  "timeout": false,
  "testStarted": 1774987342330,
  "testFinished": 1774987350200,
  "data": {
    "requests": [
      {
        "url": "https://t-msedge.net/",
        "method": "GET",
        "type": "Document",
        "size": 183807,
        "responseBodyHash": "414b06a826cbd94e0ec99efc6130d1c9168cf478023f74309e7dd2e84b8ccc55",
        "failureReason": "net::ERR_NAME_NOT_RESOLVED",
        "initiators": [],
        "time": 0.14784200000030978
      }
    ],
    "cookies": [],
    "targets": [
      {
        "type": "page",
        "url": "about:blank"
      }
    ],
    "apis": {
      "callStats": {},
      "savedCalls": []
    }
  }
}