{
  "initialUrl": "https://tiktokcdn.com/",
  "finalUrl": "chrome-error://chromewebdata/",
  "timeout": false,
  "testStarted": 1774987048370,
  "testFinished": 1774987053654,
  "data": {
    "requests": [
      {
        "url": "https://tiktokcdn.com/",
        "method": "GET",
        "type": "Document",
        "size": 183811,
        "responseBodyHash": "3d26de598b89aa863686c9cb4d076adc3dfaaec5173e794a9b4eaa7670174752",
        "failureReason": "net::ERR_NAME_NOT_RESOLVED",
        "initiators": [],
        "time": 0.05851000000075146
      }
    ],
    "cookies": [],
    "targets": [
      {
        "type": "page",
        "url": "about:blank"
      }
    ],
    "apis": {
      "callStats": {},
      "savedCalls": []
    }
  }
}